ContrailScrape/__init__.py
ContrailScrape/__main__.py
ContrailScrape/analytics_uves.py
ContrailScrape/base.py
ContrailScrape/config_parser.py
ContrailScrape/introspects.py
ContrailScrape/main.py
ContrailScrape/main_logger.py
ContrailScrape/metadata.py
ContrailScrape/scrape_ist.py
ContrailScrape/data/hosts.yaml
ContrailScrape/data/metadata.yaml
contrail_scrape-0.1.13.dist-info/LICENSE
contrail_scrape-0.1.13.dist-info/METADATA
contrail_scrape-0.1.13.dist-info/WHEEL
contrail_scrape-0.1.13.dist-info/entry_points.txt
contrail_scrape-0.1.13.dist-info/top_level.txt
contrail_scrape-0.1.13.dist-info/RECORD
