Metadata-Version: 2.1
Name: contrail-scrape
Version: 0.1.13
Summary: crawler for all the APIs of Juniper Contrail nodes
Home-page: https://github.com/aniruddhamonker/contrail-scrape
Author: Aniruddh Amonker
Author-email: aamonker@juniper.net
License: MIT
Platform: UNKNOWN
Classifier: License :: OSI Approved :: GNU General Public License v3 (GPLv3)
Classifier: Programming Language :: Python :: 3.5
Classifier: Programming Language :: Python :: 3.6
Classifier: Programming Language :: Python :: 3.8
Requires-Dist: beautifulsoup4
Requires-Dist: tqdm (==4.48.2)
Requires-Dist: PrettyTable (==0.7.2)
Requires-Dist: lxml
Requires-Dist: html5lib
Requires-Dist: requests (>=2.9.1)
Requires-Dist: PyYAML
